jirator/__init__.py
jirator/assignaction.py
jirator/constant.py
jirator/jiraaction.py
jirator/jirator.py
jirator/log.py
jirator/userdata.py
jirator/workaction.py
jirator-0.1.4.dist-info/METADATA
jirator-0.1.4.dist-info/RECORD
jirator-0.1.4.dist-info/WHEEL
jirator-0.1.4.dist-info/entry_points.txt
jirator-0.1.4.dist-info/top_level.txt
