Metadata-Version: 2.1
Name: jirator
Version: 0.1.4
Summary: Fetch your assigned JIRA issues and checkout new branches with their ID
Home-page: https://github.com/hawry/jirator
Author: hawry
Author-email: hawry@hawry.net
License: UNKNOWN
Platform: UNKNOWN
Classifier: Programming Language :: Python :: 2.7
Classifier: License :: OSI Approved :: MIT License
Classifier: Operating System :: POSIX :: Linux
Classifier: Development Status :: 3 - Alpha
Requires-Dist: console-menu
Requires-Dist: jira
Requires-Dist: click
